volt/__init__.py
volt/add_cli.py
volt/build_cli.py
volt/cli.py
volt/core/__init__.py
volt/core/config.py
volt/core/dependencies.py
volt/core/injectors.py
volt/core/prompts.py
volt/core/template.py
volt/db_cli.py
volt/py.typed
volt/stacks/__init__.py
volt/stacks/constants.py
volt/stacks/fastapi/__init__.py
volt/stacks/fastapi/adder.py
volt/stacks/fastapi/app_creator.py
volt/stacks/fastapi/cli.py
volt/stacks/fastapi/config_blocks.py
volt/stacks/fastapi/dependencies.py
volt/stacks/fastapi/docker_config.py
volt/stacks/fastapi/docker_utils.py
volt/stacks/fastapi/helpers.py
volt/stacks/fastapi/injectors.py
volt/stacks/fastapi/scaffold.py
volt/stacks/fastapi/template_utils.py
volt/templates/__init__.py
volt/templates/fastapi/__init__.py
volt/templates/fastapi/alembic/alembic.ini
volt/templates/fastapi/alembic/migrations/env.py
volt/templates/fastapi/alembic/migrations/script.py.mako
volt/templates/fastapi/auth_bearer/app/core/security.py
volt/templates/fastapi/auth_bearer/app/dependencies/__init__.py
volt/templates/fastapi/auth_bearer/app/models/user.py
volt/templates/fastapi/auth_bearer/app/routers/auth/__init__.py
volt/templates/fastapi/auth_bearer/app/routers/users/__init__.py
volt/templates/fastapi/auth_bearer/app/routers/users/routes.py
volt/templates/fastapi/auth_bearer/app/schemas/auth.py
volt/templates/fastapi/auth_bearer_model/mongo/app/dependencies/auth.py
volt/templates/fastapi/auth_bearer_model/mongo/app/routers/auth/routes.py
volt/templates/fastapi/auth_bearer_model/sqlmodel/app/dependencies/auth.py
volt/templates/fastapi/auth_bearer_model/sqlmodel/app/routers/auth/routes.py
volt/templates/fastapi/auth_cookie/app/core/security.py
volt/templates/fastapi/auth_cookie/app/dependencies/__init__.py
volt/templates/fastapi/auth_cookie/app/models/user.py
volt/templates/fastapi/auth_cookie/app/routers/auth/__init__.py
volt/templates/fastapi/auth_cookie/app/routers/users/__init__.py
volt/templates/fastapi/auth_cookie/app/routers/users/router.py
volt_cli-0.1.2.dist-info/WHEEL
volt_cli-0.1.2.dist-info/entry_points.txt
volt_cli-0.1.2.dist-info/METADATA
volt_cli-0.1.2.dist-info/RECORD
