Metadata-Version: 2.3
Name: volt-cli
Version: 0.1.2
Summary: An extremely fast template and stack manager for Python projects.
Author: Vishwa Kumaran
Author-email: Vishwa Kumaran <vishwaa33400@gmail.com>
License: MIT
Classifier: Programming Language :: Python :: 3
Classifier: License :: OSI Approved :: MIT License
Classifier: Operating System :: OS Independent
Classifier: Framework :: FastAPI
Classifier: Topic :: Software Development :: Code Generators
Requires-Dist: black>=25.9.0
Requires-Dist: pydantic>=2.0.0
Requires-Dist: questionary>=2.1.1
Requires-Dist: tomli>=2.3.0
Requires-Dist: tomli-w>=1.2.0
Requires-Dist: typer>=0.19.2
Requires-Dist: alembic>=1.13.0
Requires-Dist: pyyaml>=6.0.3
Requires-Python: >=3.13
